Webshare/Webshare.py
Webshare-1.0.0.dist-info/DESCRIPTION.rst
Webshare-1.0.0.dist-info/METADATA
Webshare-1.0.0.dist-info/RECORD
Webshare-1.0.0.dist-info/WHEEL
Webshare-1.0.0.dist-info/metadata.json
Webshare-1.0.0.dist-info/top_level.txt
